{
  "measurements": [
    {
      "location": "Yamunotri",
      "date": null,
      "month": null,
      "year": 2020,
      "season": null,
      "parameter": "pH",
      "actual_value": "7.4",
      "mean": null,
      "std_dev": null,
      "unit": null,
      "source": "Table 7",
      "notes": "Data from CPCB (2020) (CPCB 2021 annexure VI (a)). Location monitored on yearly basis."
    },
    {
      "location": "Yamunotri",
      "date": null,
      "month": null,
      "year": 2020,
      "season": null,
      "parameter": "Dissolved Oxygen",
      "actual_value": "10.8",
      "mean": null,
      "std_dev": null,
      "unit": "mg/L",
      "source": "Table 7",
      "notes": "Data from CPCB (2020) (CPCB 2021 annexure VI (a)). BDL value for DO is 3.0 mg/L as per table footnote. Location monitored on yearly basis."
    },
    {
      "location": "Yamunotri",
      "date": null,
      "month": null,
      "year": 2020,
      "season": null,
      "parameter": "Electrical Conductivity",
      "actual_value": "79",
      "mean": null,
      "std_dev": null,
      "unit": "\u00b5mhos/cm",
      "source": "Table 7",
      "notes": "Data from CPCB (2020) (CPCB 2021 annexure VI (a)). Location monitored on yearly basis."
    },
    {
      "location": "Yamunotri",
      "date": null,
      "month": null,
      "year": 2020,
      "season": null,
      "parameter": "Biochemical Oxygen Demand",
      "actual_value": "BDL",
      "mean": null,
      "std_dev": null,
      "unit": "mg/L",
      "source": "Table 7",
      "notes": "Data from CPCB (2020) (CPCB 2021 annexure VI (a)). Location monitored on yearly basis."
    },
    {
      "location": "Yamunotri",
      "date": null,
      "month": null,
      "year": 2020,
      "season": null,
      "parameter": "Fecal Coliform",
      "actual_value": "4",
      "mean": null,
      "std_dev": null,
      "unit": "MPN/100 mL",
      "source": "Table 7",
      "notes": "Data from CPCB (2020) (CPCB 2021 annexure VI (a)). Location monitored on yearly basis."
    },
    {
      "location": "Yamunotri",
      "date": null,
      "month": null,
      "year": 2020,
      "season": null,
      "parameter": "Total Coliform",
      "actual_value": "4",
      "mean": null,
      "std_dev": null,
      "unit": "MPN/100 mL",
      "source": "Table 7",
      "notes": "Data from CPCB (2020) (CPCB 2021 annexure VI (a)). Location monitored on yearly basis."
    },
    {
      "location": "Hanumanchatti",
      "date": null,
      "month": null,
      "year": 2020,
      "season": null,
      "parameter": "pH",
      "actual_value": "7.9",
      "mean": null,
      "std_dev": null,
      "unit": null,
      "source": "Table 7",
      "notes": "Data from CPCB (2020) (CPCB 2021 annexure VI (a)). Location monitored on yearly basis."
    },
    {
      "location": "Hanumanchatti",
      "date": null,
      "month": null,
      "year": 2020,
      "season": null,
      "parameter": "Dissolved Oxygen",
      "actual_value": "11.6",
      "mean": null,
      "std_dev": null,
      "unit": "mg/L",
      "source": "Table 7",
      "notes": "Data from CPCB (2020) (CPCB 2021 annexure VI (a)). BDL value for DO is 3.0 mg/L as per table footnote. Location monitored on yearly basis."
    },
    {
      "location": "Hanumanchatti",
      "date": null,
      "month": null,
      "year": 2020,
      "season": null,
      "parameter": "Electrical Conductivity",
      "actual_value": "145",
      "mean": null,
      "std_dev": null,
      "unit": "\u00b5mhos/cm",
      "source": "Table 7",
      "notes": "Data from CPCB (2020) (CPCB 2021 annexure VI (a)). Location monitored on yearly basis."
    },
    {
      "location": "Hanumanchatti",
      "date": null,
      "month": null,
      "year": 2020,
      "season": null,
      "parameter": "Biochemical Oxygen Demand",
      "actual_value": "BDL",
      "mean": null,
      "std_dev": null,
      "unit": "mg/L",
      "source": "Table 7",
      "notes": "Data from CPCB (2020) (CPCB 2021 annexure VI (a)). Location monitored on yearly basis."
    },
    {
      "location": "Hanumanchatti",
      "date": null,
      "month": null,
      "year": 2020,
      "season": null,
      "parameter": "Fecal Coliform",
      "actual_value": "94",
      "mean": null,
      "std_dev": null,
      "unit": "MPN/100 mL",
      "source": "Table 7",
      "notes": "Data from CPCB (2020) (CPCB 2021 annexure VI (a)). Location monitored on yearly basis."
    },
    {
      "location": "Hanumanchatti",
      "date": null,
      "month": null,
      "year": 2020,
      "season": null,
      "parameter": "Total Coliform",
      "actual_value": "140",
      "mean": null,
      "std_dev": null,
      "unit": "MPN/100 mL",
      "source": "Table 7",
      "notes": "Data from CPCB (2020) (CPCB 2021 annexure VI (a)). Location monitored on yearly basis."
    },
    {
      "location": "U/S Lakhwar Dam",
      "date": null,
      "month": null,
      "year": 2020,
      "season": null,
      "parameter": "Temperature",
      "actual_value": "16-22",
      "mean": null,
      "std_dev": null,
      "unit": "\u00b0C",
      "source": "Table 7",
      "notes": "Data from CPCB (2020) (CPCB 2021 annexure VI (a))."
    },
    {
      "location": "U/S Lakhwar Dam",
      "date": null,
      "month": null,
      "year": 2020,
      "season": null,
      "parameter": "pH",
      "actual_value": "7.7-8.4",
      "mean": null,
      "std_dev": null,
      "unit": null,
      "source": "Table 7",
      "notes": "Data from CPCB (2020) (CPCB 2021 annexure VI (a))."
    },
    {
      "location": "U/S Lakhwar Dam",
      "date": null,
      "month": null,
      "year": 2020,
      "season": null,
      "parameter": "Dissolved Oxygen",
      "actual_value": "8.6-10.8",
      "mean": null,
      "std_dev": null,
      "unit": "mg/L",
      "source": "Table 7",
      "notes": "Data from CPCB (2020) (CPCB 2021 annexure VI (a)). BDL value for DO is 3.0 mg/L as per table footnote."
    },
    {
      "location": "U/S Lakhwar Dam",
      "date": null,
      "month": null,
      "year": 2020,
      "season": null,
      "parameter": "Electrical Conductivity",
      "actual_value": "142-320",
      "mean": null,
      "std_dev": null,
      "unit": "\u00b5mhos/cm",
      "source": "Table 7",
      "notes": "Data from CPCB (2020) (CPCB 2021 annexure VI (a))."
    },
    {
      "location": "U/S Lakhwar Dam",
      "date": null,
      "month": null,
      "year": 2020,
      "season": null,
      "parameter": "Biochemical Oxygen Demand",
      "actual_value": "0.8-1.0",
      "mean": null,
      "std_dev": null,
      "unit": "mg/L",
      "source": "Table 7",
      "notes": "Data from CPCB (2020) (CPCB 2021 annexure VI (a))."
    },
    {
      "location": "U/S Lakhwar Dam",
      "date": null,
      "month": null,
      "year": 2020,
      "season": null,
      "parameter": "Fecal Coliform",
      "actual_value": "2-9",
      "mean": null,
      "std_dev": null,
      "unit": "MPN/100 mL",
      "source": "Table 7",
      "notes": "Data from CPCB (2020) (CPCB 2021 annexure VI (a))."
    },
    {
      "location": "U/S Lakhwar Dam",
      "date": null,
      "month": null,
      "year": 2020,
      "season": null,
      "parameter": "Total Coliform",
      "actual_value": "2-30",
      "mean": null,
      "std_dev": null,
      "unit": "MPN/100 mL",
      "source": "Table 7",
      "notes": "Data from CPCB (2020) (CPCB 2021 annexure VI (a))."
    },
    {
      "location": "U/S Dak Patthar",
      "date": null,
      "month": null,
      "year": 2020,
      "season": null,
      "parameter": "Temperature",
      "actual_value": "17-24",
      "mean": null,
      "std_dev": null,
      "unit": "\u00b0C",
      "source": "Table 7",
      "notes": "Data from CPCB (2020) (CPCB 2021 annexure VI (a))."
    },
    {
      "location": "U/S Dak Patthar",
      "date": null,
      "month": null,
      "year": 2020,
      "season": null,
      "parameter": "pH",
      "actual_value": "8.0-8.2",
      "mean": null,
      "std_dev": null,
      "unit": null,
      "source": "Table 7",
      "notes": "Data from CPCB (2020) (CPCB 2021 annexure VI (a))."
    },
    {
      "location": "U/S Dak Patthar",
      "date": null,
      "month": null,
      "year": 2020,
      "season": null,
      "parameter": "Dissolved Oxygen",
      "actual_value": "8.2-10.2",
      "mean": null,
      "std_dev": null,
      "unit": "mg/L",
      "source": "Table 7",
      "notes": "Data from CPCB (2020) (CPCB 2021 annexure VI (a)). BDL value for DO is 3.0 mg/L as per table footnote."
    },
    {
      "location": "U/S Dak Patthar",
      "date": null,
      "month": null,
      "year": 2020,
      "season": null,
      "parameter": "Electrical Conductivity",
      "actual_value": "106-162",
      "mean": null,
      "std_dev": null,
      "unit": "\u00b5mhos/cm",
      "source": "Table 7",
      "notes": "Data from CPCB (2020) (CPCB 2021 annexure VI (a))."
    },
    {
      "location": "U/S Dak Patthar",
      "date": null,
      "month": null,
      "year": 2020,
      "season": null,
      "parameter": "Biochemical Oxygen Demand",
      "actual_value": "1.0-1.2",
      "mean": null,
      "std_dev": null,
      "unit": "mg/L",
      "source": "Table 7",
      "notes": "Data from CPCB (2020) (CPCB 2021 annexure VI (a))."
    },
    {
      "location": "U/S Dak Patthar",
      "date": null,
      "month": null,
      "year": 2020,
      "season": null,
      "parameter": "Fecal Coliform",
      "actual_value": "17-34",
      "mean": null,
      "std_dev": null,
      "unit": "MPN/100 mL",
      "source": "Table 7",
      "notes": "Data from CPCB (2020) (CPCB 2021 annexure VI (a))."
    },
    {
      "location": "U/S Dak Patthar",
      "date": null,
      "month": null,
      "year": 2020,
      "season": null,
      "parameter": "Total Coliform",
      "actual_value": "40-70",
      "mean": null,
      "std_dev": null,
      "unit": "MPN/100 mL",
      "source": "Table 7",
      "notes": "Data from CPCB (2020) (CPCB 2021 annexure VI (a))."
    },
    {
      "location": "U/S Paonta Sahib",
      "date": null,
      "month": null,
      "year": 2020,
      "season": null,
      "parameter": "Temperature",
      "actual_value": "13-28",
      "mean": null,
      "std_dev": null,
      "unit": "\u00b0C",
      "source": "Table 7",
      "notes": "Data from CPCB (2020) (CPCB 2021 annexure VI (a))."
    },
    {
      "location": "U/S Paonta Sahib",
      "date": null,
      "month": null,
      "year": 2020,
      "season": null,
      "parameter": "pH",
      "actual_value": "6.4-8.0",
      "mean": null,
      "std_dev": null,
      "unit": null,
      "source": "Table 7",
      "notes": "Data from CPCB (2020) (CPCB 2021 annexure VI (a))."
    },
    {
      "location": "U/S Paonta Sahib",
      "date": null,
      "month": null,
      "year": 2020,
      "season": null,
      "parameter": "Dissolved Oxygen",
      "actual_value": "7.1-9.1",
      "mean": null,
      "std_dev": null,
      "unit": "mg/L",
      "source": "Table 7",
      "notes": "Data from CPCB (2020) (CPCB 2021 annexure VI (a)). BDL value for DO is 3.0 mg/L as per table footnote."
    },
    {
      "location": "U/S Paonta Sahib",
      "date": null,
      "month": null,
      "year": 2020,
      "season": null,
      "parameter": "Electrical Conductivity",
      "actual_value": "214-5866",
      "mean": null,
      "std_dev": null,
      "unit": "\u00b5mhos/cm",
      "source": "Table 7",
      "notes": "Data from CPCB (2020) (CPCB 2021 annexure VI (a))."
    },
    {
      "location": "U/S Paonta Sahib",
      "date": null,
      "month": null,
      "year": 2020,
      "season": null,
      "parameter": "Biochemical Oxygen Demand",
      "actual_value": "0.4-1.8",
      "mean": null,
      "std_dev": null,
      "unit": "mg/L",
      "source": "Table 7",
      "notes": "Data from CPCB (2020) (CPCB 2021 annexure VI (a))."
    },
    {
      "location": "U/S Paonta Sahib",
      "date": null,
      "month": null,
      "year": 2020,
      "season": null,
      "parameter": "Fecal Coliform",
      "actual_value": "9-46",
      "mean": null,
      "std_dev": null,
      "unit": "MPN/100 mL",
      "source": "Table 7",
      "notes": "Data from CPCB (2020) (CPCB 2021 annexure VI (a))."
    },
    {
      "location": "U/S Paonta Sahib",
      "date": null,
      "month": null,
      "year": 2020,
      "season": null,
      "parameter": "Total Coliform",
      "actual_value": "32-140",
      "mean": null,
      "std_dev": null,
      "unit": "MPN/100 mL",
      "source": "Table 7",
      "notes": "Data from CPCB (2020) (CPCB 2021 annexure VI (a))."
    },
    {
      "location": "D/S Paonta Sahib",
      "date": null,
      "month": null,
      "year": 2020,
      "season": null,
      "parameter": "Temperature",
      "actual_value": "11-31",
      "mean": null,
      "std_dev": null,
      "unit": "\u00b0C",
      "source": "Table 7",
      "notes": "Data from CPCB (2020) (CPCB 2021 annexure VI (a))."
    },
    {
      "location": "D/S Paonta Sahib",
      "date": null,
      "month": null,
      "year": 2020,
      "season": null,
      "parameter": "pH",
      "actual_value": "6.6-7.7",
      "mean": null,
      "std_dev": null,
      "unit": null,
      "source": "Table 7",
      "notes": "Data from CPCB (2020) (CPCB 2021 annexure VI (a))."
    },
    {
      "location": "D/S Paonta Sahib",
      "date": null,
      "month": null,
      "year": 2020,
      "season": null,
      "parameter": "Dissolved Oxygen",
      "actual_value": "7.0-9.0",
      "mean": null,
      "std_dev": null,
      "unit": "mg/L",
      "source": "Table 7",
      "notes": "Data from CPCB (2020) (CPCB 2021 annexure VI (a)). BDL value for DO is 3.0 mg/L as per table footnote."
    },
    {
      "location": "D/S Paonta Sahib",
      "date": null,
      "month": null,
      "year": 2020,
      "season": null,
      "parameter": "Electrical Conductivity",
      "actual_value": "248-448",
      "mean": null,
      "std_dev": null,
      "unit": "\u00b5mhos/cm",
      "source": "Table 7",
      "notes": "Data from CPCB (2020) (CPCB 2021 annexure VI (a))."
    },
    {
      "location": "D/S Paonta Sahib",
      "date": null,
      "month": null,
      "year": 2020,
      "season": null,
      "parameter": "Biochemical Oxygen Demand",
      "actual_value": "0.4-2.0",
      "mean": null,
      "std_dev": null,
      "unit": "mg/L",
      "source": "Table 7",
      "notes": "Data from CPCB (2020) (CPCB 2021 annexure VI (a))."
    },
    {
      "location": "D/S Paonta Sahib",
      "date": null,
      "month": null,
      "year": 2020,
      "season": null,
      "parameter": "Fecal Coliform",
      "actual_value": "11-27",
      "mean": null,
      "std_dev": null,
      "unit": "MPN/100 mL",
      "source": "Table 7",
      "notes": "Data from CPCB (2020) (CPCB 2021 annexure VI (a))."
    },
    {
      "location": "D/S Paonta Sahib",
      "date": null,
      "month": null,
      "year": 2020,
      "season": null,
      "parameter": "Total Coliform",
      "actual_value": "38-94",
      "mean": null,
      "std_dev": null,
      "unit": "MPN/100 mL",
      "source": "Table 7",
      "notes": "Data from CPCB (2020) (CPCB 2021 annexure VI (a))."
    },
    {
      "location": "U/S Ranbaxy",
      "date": null,
      "month": null,
      "year": 2020,
      "season": null,
      "parameter": "Temperature",
      "actual_value": "16-34",
      "mean": null,
      "std_dev": null,
      "unit": "\u00b0C",
      "source": "Table 7",
      "notes": "Data from CPCB (2020) (CPCB 2021 annexure VI (a))."
    },
    {
      "location": "U/S Ranbaxy",
      "date": null,
      "month": null,
      "year": 2020,
      "season": null,
      "parameter": "pH",
      "actual_value": "7.0-7.6",
      "mean": null,
      "std_dev": null,
      "unit": null,
      "source": "Table 7",
      "notes": "Data from CPCB (2020) (CPCB 2021 annexure VI (a))."
    },
    {
      "location": "U/S Ranbaxy",
      "date": null,
      "month": null,
      "year": 2020,
      "season": null,
      "parameter": "Dissolved Oxygen",
      "actual_value": "7.1-8.9",
      "mean": null,
      "std_dev": null,
      "unit": "mg/L",
      "source": "Table 7",
      "notes": "Data from CPCB (2020) (CPCB 2021 annexure VI (a)). BDL value for DO is 3.0 mg/L as per table footnote."
    },
    {
      "location": "U/S Ranbaxy",
      "date": null,
      "month": null,
      "year": 2020,
      "season": null,
      "parameter": "Electrical Conductivity",
      "actual_value": "162-605",
      "mean": null,
      "std_dev": null,
      "unit": "\u00b5mhos/cm",
      "source": "Table 7",
      "notes": "Data from CPCB (2020) (CPCB 2021 annexure VI (a))."
    },
    {
      "location": "U/S Ranbaxy",
      "date": null,
      "month": null,
      "year": 2020,
      "season": null,
      "parameter": "Biochemical Oxygen Demand",
      "actual_value": "0.4-1.6",
      "mean": null,
      "std_dev": null,
      "unit": "mg/L",
      "source": "Table 7",
      "notes": "Data from CPCB (2020) (CPCB 2021 annexure VI (a))."
    },
    {
      "location": "U/S Ranbaxy",
      "date": null,
      "month": null,
      "year": 2020,
      "season": null,
      "parameter": "Fecal Coliform",
      "actual_value": "10-13",
      "mean": null,
      "std_dev": null,
      "unit": "MPN/100 mL",
      "source": "Table 7",
      "notes": "Data from CPCB (2020) (CPCB 2021 annexure VI (a))."
    },
    {
      "location": "U/S Ranbaxy",
      "date": null,
      "month": null,
      "year": 2020,
      "season": null,
      "parameter": "Total Coliform",
      "actual_value": "32-94",
      "mean": null,
      "std_dev": null,
      "unit": "MPN/100 mL",
      "source": "Table 7",
      "notes": "Data from CPCB (2020) (CPCB 2021 annexure VI (a))."
    },
    {
      "location": "D/S Ranbaxy",
      "date": null,
      "month": null,
      "year": 2020,
      "season": null,
      "parameter": "Temperature",
      "actual_value": "16-34",
      "mean": null,
      "std_dev": null,
      "unit": "\u00b0C",
      "source": "Table 7",
      "notes": "Data from CPCB (2020) (CPCB 2021 annexure VI (a))."
    },
    {
      "location": "D/S Ranbaxy",
      "date": null,
      "month": null,
      "year": 2020,
      "season": null,
      "parameter": "pH",
      "actual_value": "7.0-7.6",
      "mean": null,
      "std_dev": null,
      "unit": null,
      "source": "Table 7",
      "notes": "Data from CPCB (2020) (CPCB 2021 annexure VI (a))."
    },
    {
      "location": "D/S Ranbaxy",
      "date": null,
      "month": null,
      "year": 2020,
      "season": null,
      "parameter": "Dissolved Oxygen",
      "actual_value": "7.0-8.8",
      "mean": null,
      "std_dev": null,
      "unit": "mg/L",
      "source": "Table 7",
      "notes": "Data from CPCB (2020) (CPCB 2021 annexure VI (a)). BDL value for DO is 3.0 mg/L as per table footnote."
    },
    {
      "location": "D/S Ranbaxy",
      "date": null,
      "month": null,
      "year": 2020,
      "season": null,
      "parameter": "Electrical Conductivity",
      "actual_value": "161-2593",
      "mean": null,
      "std_dev": null,
      "unit": "\u00b5mhos/cm",
      "source": "Table 7",
      "notes": "Data from CPCB (2020) (CPCB 2021 annexure VI (a))."
    },
    {
      "location": "D/S Ranbaxy",
      "date": null,
      "month": null,
      "year": 2020,
      "season": null,
      "parameter": "Biochemical Oxygen Demand",
      "actual_value": "0.4-1.8",
      "mean": null,
      "std_dev": null,
      "unit": "mg/L",
      "source": "Table 7",
      "notes": "Data from CPCB (2020) (CPCB 2021 annexure VI (a))."
    },
    {
      "location": "D/S Ranbaxy",
      "date": null,
      "month": null,
      "year": 2020,
      "season": null,
      "parameter": "Fecal Coliform",
      "actual_value": "10-33",
      "mean": null,
      "std_dev": null,
      "unit": "MPN/100 mL",
      "source": "Table 7",
      "notes": "Data from CPCB (2020) (CPCB 2021 annexure VI (a))."
    },
    {
      "location": "D/S Ranbaxy",
      "date": null,
      "month": null,
      "year": 2020,
      "season": null,
      "parameter": "Total Coliform",
      "actual_value": "33-110",
      "mean": null,
      "std_dev": null,
      "unit": "MPN/100 mL",
      "source": "Table 7",
      "notes": "Data from CPCB (2020) (CPCB 2021 annexure VI (a))."
    },
    {
      "location": "Hathnikund, Yamunanagar",
      "date": null,
      "month": null,
      "year": 2020,
      "season": null,
      "parameter": "Temperature",
      "actual_value": "21-29",
      "mean": null,
      "std_dev": null,
      "unit": "\u00b0C",
      "source": "Table 7",
      "notes": "Data from CPCB (2020) (CPCB 2021 annexure VI (a))."
    },
    {
      "location": "Hathnikund, Yamunanagar",
      "date": null,
      "month": null,
      "year": 2020,
      "season": null,
      "parameter": "pH",
      "actual_value": "7.3-8.3",
      "mean": null,
      "std_dev": null,
      "unit": null,
      "source": "Table 7",
      "notes": "Data from CPCB (2020) (CPCB 2021 annexure VI (a))."
    },
    {
      "location": "Hathnikund, Yamunanagar",
      "date": null,
      "month": null,
      "year": 2020,
      "season": null,
      "parameter": "Dissolved Oxygen",
      "actual_value": "7.1-8.5",
      "mean": null,
      "std_dev": null,
      "unit": "mg/L",
      "source": "Table 7",
      "notes": "Data from CPCB (2020) (CPCB 2021 annexure VI (a)). BDL value for DO is 3.0 mg/L as per table footnote."
    },
    {
      "location": "Hathnikund, Yamunanagar",
      "date": null,
      "month": null,
      "year": 2020,
      "season": null,
      "parameter": "Electrical Conductivity",
      "actual_value": "192-620",
      "mean": null,
      "std_dev": null,
      "unit": "\u00b5mhos/cm",
      "source": "Table 7",
      "notes": "Data from CPCB (2020) (CPCB 2021 annexure VI (a))."
    },
    {
      "location": "Hathnikund, Yamunanagar",
      "date": null,
      "month": null,
      "year": 2020,
      "season": null,
      "parameter": "Biochemical Oxygen Demand",
      "actual_value": "2.4-6.6",
      "mean": null,
      "std_dev": null,
      "unit": "mg/L",
      "source": "Table 7",
      "notes": "Data from CPCB (2020) (CPCB 2021 annexure VI (a))."
    },
    {
      "location": "Hathnikund, Yamunanagar",
      "date": null,
      "month": null,
      "year": 2020,
      "season": null,
      "parameter": "Fecal Coliform",
      "actual_value": "200-3200",
      "mean": null,
      "std_dev": null,
      "unit": "MPN/100 mL",
      "source": "Table 7",
      "notes": "Data from CPCB (2020) (CPCB 2021 annexure VI (a))."
    },
    {
      "location": "Hathnikund, Yamunanagar",
      "date": null,
      "month": null,
      "year": 2020,
      "season": null,
      "parameter": "Total Coliform",
      "actual_value": "1100-21200",
      "mean": null,
      "std_dev": null,
      "unit": "MPN/100 mL",
      "source": "Table 7",
      "notes": "Data from CPCB (2020) (CPCB 2021 annexure VI (a))."
    },
    {
      "location": "Kalanaur, Yamunanagar",
      "date": null,
      "month": null,
      "year": 2020,
      "season": null,
      "parameter": "Temperature",
      "actual_value": "19-29",
      "mean": null,
      "std_dev": null,
      "unit": "\u00b0C",
      "source": "Table 7",
      "notes": "Data from CPCB (2020) (CPCB 2021 annexure VI (a))."
    },
    {
      "location": "Kalanaur, Yamunanagar",
      "date": null,
      "month": null,
      "year": 2020,
      "season": null,
      "parameter": "pH",
      "actual_value": "7.2-8.3",
      "mean": null,
      "std_dev": null,
      "unit": null,
      "source": "Table 7",
      "notes": "Data from CPCB (2020) (CPCB 2021 annexure VI (a))."
    },
    {
      "location": "Kalanaur, Yamunanagar",
      "date": null,
      "month": null,
      "year": 2020,
      "season": null,
      "parameter": "Dissolved Oxygen",
      "actual_value": "6.8-9.3",
      "mean": null,
      "std_dev": null,
      "unit": "mg/L",
      "source": "Table 7",
      "notes": "Data from CPCB (2020) (CPCB 2021 annexure VI (a)). BDL value for DO is 3.0 mg/L as per table footnote."
    },
    {
      "location": "Kalanaur, Yamunanagar",
      "date": null,
      "month": null,
      "year": 2020,
      "season": null,
      "parameter": "Electrical Conductivity",
      "actual_value": "197-608",
      "mean": null,
      "std_dev": null,
      "unit": "\u00b5mhos/cm",
      "source": "Table 7",
      "notes": "Data from CPCB (2020) (CPCB 2021 annexure VI (a))."
    },
    {
      "location": "Kalanaur, Yamunanagar",
      "date": null,
      "month": null,
      "year": 2020,
      "season": null,
      "parameter": "Biochemical Oxygen Demand",
      "actual_value": "2.2-5.2",
      "mean": null,
      "std_dev": null,
      "unit": "mg/L",
      "source": "Table 7",
      "notes": "Data from CPCB (2020) (CPCB 2021 annexure VI (a))."
    },
    {
      "location": "Kalanaur, Yamunanagar",
      "date": null,
      "month": null,
      "year": 2020,
      "season": null,
      "parameter": "Fecal Coliform",
      "actual_value": "200-49000",
      "mean": null,
      "std_dev": null,
      "unit": "MPN/100 mL",
      "source": "Table 7",
      "notes": "Data from CPCB (2020) (CPCB 2021 annexure VI (a))."
    },
    {
      "location": "Kalanaur, Yamunanagar",
      "date": null,
      "month": null,
      "year": 2020,
      "season": null,
      "parameter": "Total Coliform",
      "actual_value": "3900-1600000",
      "mean": null,
      "std_dev": null,
      "unit": "MPN/100 mL",
      "source": "Table 7",
      "notes": "Data from CPCB (2020) (CPCB 2021 annexure VI (a))."
    },
    {
      "location": "Magalaura",
      "date": null,
      "month": null,
      "year": 2020,
      "season": null,
      "parameter": "pH",
      "actual_value": "7.2-8.5",
      "mean": null,
      "std_dev": null,
      "unit": null,
      "source": "Table 7",
      "notes": "Data from CPCB (2020) (CPCB 2021 annexure VI (a))."
    },
    {
      "location": "Magalaura",
      "date": null,
      "month": null,
      "year": 2020,
      "season": null,
      "parameter": "Dissolved Oxygen",
      "actual_value": "5.2-10.8",
      "mean": null,
      "std_dev": null,
      "unit": "mg/L",
      "source": "Table 7",
      "notes": "Data from CPCB (2020) (CPCB 2021 annexure VI (a)). BDL value for DO is 3.0 mg/L as per table footnote."
    },
    {
      "location": "Magalaura",
      "date": null,
      "month": null,
      "year": 2020,
      "season": null,
      "parameter": "Electrical Conductivity",
      "actual_value": "157-451",
      "mean": null,
      "std_dev": null,
      "unit": "\u00b5mhos/cm",
      "source": "Table 7",
      "notes": "Data from CPCB (2020) (CPCB 2021 annexure VI (a))."
    },
    {
      "location": "Magalaura",
      "date": null,
      "month": null,
      "year": 2020,
      "season": null,
      "parameter": "Biochemical Oxygen Demand",
      "actual_value": "BDL-4.0",
      "mean": null,
      "std_dev": null,
      "unit": "mg/L",
      "source": "Table 7",
      "notes": "Data from CPCB (2020) (CPCB 2021 annexure VI (a))."
    },
    {
      "location": "Magalaura",
      "date": null,
      "month": null,
      "year": 2020,
      "season": null,
      "parameter": "Fecal Coliform",
      "actual_value": "49-7000",
      "mean": null,
      "std_dev": null,
      "unit": "MPN/100 mL",
      "source": "Table 7",
      "notes": "Data from CPCB (2020) (CPCB 2021 annexure VI (a))."
    },
    {
      "location": "Magalaura",
      "date": null,
      "month": null,
      "year": 2020,
      "season": null,
      "parameter": "Total Coliform",
      "actual_value": "230-35000",
      "mean": null,
      "std_dev": null,
      "unit": "MPN/100 mL",
      "source": "Table 7",
      "notes": "Data from CPCB (2020) (CPCB 2021 annexure VI (a))."
    },
    {
      "location": "Khojkipur, Panipat",
      "date": null,
      "month": null,
      "year": 2020,
      "season": null,
      "parameter": "Temperature",
      "actual_value": "21-29",
      "mean": null,
      "std_dev": null,
      "unit": "\u00b0C",
      "source": "Table 7",
      "notes": "Data from CPCB (2020) (CPCB 2021 annexure VI (a))."
    },
    {
      "location": "Khojkipur, Panipat",
      "date": null,
      "month": null,
      "year": 2020,
      "season": null,
      "parameter": "pH",
      "actual_value": "6.6-8.4",
      "mean": null,
      "std_dev": null,
      "unit": null,
      "source": "Table 7",
      "notes": "Data from CPCB (2020) (CPCB 2021 annexure VI (a))."
    },
    {
      "location": "Khojkipur, Panipat",
      "date": null,
      "month": null,
      "year": 2020,
      "season": null,
      "parameter": "Dissolved Oxygen",
      "actual_value": "5.0-8.4",
      "mean": null,
      "std_dev": null,
      "unit": "mg/L",
      "source": "Table 7",
      "notes": "Data from CPCB (2020) (CPCB 2021 annexure VI (a)). BDL value for DO is 3.0 mg/L as per table footnote."
    },
    {
      "location": "Khojkipur, Panipat",
      "date": null,
      "month": null,
      "year": 2020,
      "season": null,
      "parameter": "Electrical Conductivity",
      "actual_value": "255-942",
      "mean": null,
      "std_dev": null,
      "unit": "\u00b5mhos/cm",
      "source": "Table 7",
      "notes": "Data from CPCB (2020) (CPCB 2021 annexure VI (a))."
    },
    {
      "location": "Khojkipur, Panipat",
      "date": null,
      "month": null,
      "year": 2020,
      "season": null,
      "parameter": "Biochemical Oxygen Demand",
      "actual_value": "1.4-7.0",
      "mean": null,
      "std_dev": null,
      "unit": "mg/L",
      "source": "Table 7",
      "notes": "Data from CPCB (2020) (CPCB 2021 annexure VI (a))."
    },
    {
      "location": "Khojkipur, Panipat",
      "date": null,
      "month": null,
      "year": 2020,
      "season": null,
      "parameter": "Fecal Coliform",
      "actual_value": "90-70000",
      "mean": null,
      "std_dev": null,
      "unit": "MPN/100 mL",
      "source": "Table 7",
      "notes": "Data from CPCB (2020) (CPCB 2021 annexure VI (a))."
    },
    {
      "location": "Khojkipur, Panipat",
      "date": null,
      "month": null,
      "year": 2020,
      "season": null,
      "parameter": "Total Coliform",
      "actual_value": "270-278000",
      "mean": null,
      "std_dev": null,
      "unit": "MPN/100 mL",
      "source": "Table 7",
      "notes": "Data from CPCB (2020) (CPCB 2021 annexure VI (a))."
    },
    {
      "location": "Sonepat",
      "date": null,
      "month": null,
      "year": 2020,
      "season": null,
      "parameter": "Temperature",
      "actual_value": "14-35",
      "mean": null,
      "std_dev": null,
      "unit": "\u00b0C",
      "source": "Table 7",
      "notes": "Data from CPCB (2020) (CPCB 2021 annexure VI (a))."
    },
    {
      "location": "Sonepat",
      "date": null,
      "month": null,
      "year": 2020,
      "season": null,
      "parameter": "pH",
      "actual_value": "6.5-8.6",
      "mean": null,
      "std_dev": null,
      "unit": null,
      "source": "Table 7",
      "notes": "Data from CPCB (2020) (CPCB 2021 annexure VI (a))."
    },
    {
      "location": "Sonepat",
      "date": null,
      "month": null,
      "year": 2020,
      "season": null,
      "parameter": "Dissolved Oxygen",
      "actual_value": "7.1-10.6",
      "mean": null,
      "std_dev": null,
      "unit": "mg/L",
      "source": "Table 7",
      "notes": "Data from CPCB (2020) (CPCB 2021 annexure VI (a)). BDL value for DO is 3.0 mg/L as per table footnote."
    },
    {
      "location": "Sonepat",
      "date": null,
      "month": null,
      "year": 2020,
      "season": null,
      "parameter": "Electrical Conductivity",
      "actual_value": "235-683",
      "mean": null,
      "std_dev": null,
      "unit": "\u00b5mhos/cm",
      "source": "Table 7",
      "notes": "Data from CPCB (2020) (CPCB 2021 annexure VI (a))."
    },
    {
      "location": "Sonepat",
      "date": null,
      "month": null,
      "year": 2020,
      "season": null,
      "parameter": "Biochemical Oxygen Demand",
      "actual_value": "1.8-5.5",
      "mean": null,
      "std_dev": null,
      "unit": "mg/L",
      "source": "Table 7",
      "notes": "Data from CPCB (2020) (CPCB 2021 annexure VI (a))."
    },
    {
      "location": "Sonepat",
      "date": null,
      "month": null,
      "year": 2020,
      "season": null,
      "parameter": "Fecal Coliform",
      "actual_value": "110-220000",
      "mean": null,
      "std_dev": null,
      "unit": "MPN/100 mL",
      "source": "Table 7",
      "notes": "Data from CPCB (2020) (CPCB 2021 annexure VI (a))."
    },
    {
      "location": "Sonepat",
      "date": null,
      "month": null,
      "year": 2020,
      "season": null,
      "parameter": "Total Coliform",
      "actual_value": "330-1600000",
      "mean": null,
      "std_dev": null,
      "unit": "MPN/100 mL",
      "source": "Table 7",
      "notes": "Data from CPCB (2020) (CPCB 2021 annexure VI (a))."
    },
    {
      "location": "Palla",
      "date": null,
      "month": null,
      "year": 2020,
      "season": null,
      "parameter": "Temperature",
      "actual_value": "16-33",
      "mean": null,
      "std_dev": null,
      "unit": "\u00b0C",
      "source": "Table 7",
      "notes": "Data from CPCB (2020) (CPCB 2021 annexure VI (a))."
    },
    {
      "location": "Palla",
      "date": null,
      "month": null,
      "year": 2020,
      "season": null,
      "parameter": "pH",
      "actual_value": "7.6-9.0",
      "mean": null,
      "std_dev": null,
      "unit": null,
      "source": "Table 7",
      "notes": "Data from CPCB (2020) (CPCB 2021 annexure VI (a))."
    },
    {
      "location": "Palla",
      "date": null,
      "month": null,
      "year": 2020,
      "season": null,
      "parameter": "Dissolved Oxygen",
      "actual_value": "5.6-17.1",
      "mean": null,
      "std_dev": null,
      "unit": "mg/L",
      "source": "Table 7",
      "notes": "Data from CPCB (2020) (CPCB 2021 annexure VI (a)). BDL value for DO is 3.0 mg/L as per table footnote."
    },
    {
      "location": "Palla",
      "date": null,
      "month": null,
      "year": 2020,
      "season": null,
      "parameter": "Electrical Conductivity",
      "actual_value": "273-789",
      "mean": null,
      "std_dev": null,
      "unit": "\u00b5mhos/cm",
      "source": "Table 7",
      "notes": "Data from CPCB (2020) (CPCB 2021 annexure VI (a))."
    },
    {
      "location": "Palla",
      "date": null,
      "month": null,
      "year": 2020,
      "season": null,
      "parameter": "Biochemical Oxygen Demand",
      "actual_value": "1.4-7.9",
      "mean": null,
      "std_dev": null,
      "unit": "mg/L",
      "source": "Table 7",
      "notes": "Data from CPCB (2020) (CPCB 2021 annexure VI (a))."
    },
    {
      "location": "Palla",
      "date": null,
      "month": null,
      "year": 2020,
      "season": null,
      "parameter": "Fecal Coliform",
      "actual_value": "78-79,000",
      "mean": null,
      "std_dev": null,
      "unit": "MPN/100 mL",
      "source": "Table 7",
      "notes": "Data from CPCB (2020) (CPCB 2021 annexure VI (a))."
    },
    {
      "location": "Palla",
      "date": null,
      "month": null,
      "year": 2020,
      "season": null,
      "parameter": "Total Coliform",
      "actual_value": "330-350000",
      "mean": null,
      "std_dev": null,
      "unit": "MPN/100 mL",
      "source": "Table 7",
      "notes": "Data from CPCB (2020) (CPCB 2021 annexure VI (a))."
    },
    {
      "location": "Nizamuddin",
      "date": null,
      "month": null,
      "year": 2020,
      "season": null,
      "parameter": "Temperature",
      "actual_value": "13-31",
      "mean": null,
      "std_dev": null,
      "unit": "\u00b0C",
      "source": "Table 7",
      "notes": "Data from CPCB (2020) (CPCB 2021 annexure VI (a))."
    },
    {
      "location": "Nizamuddin",
      "date": null,
      "month": null,
      "year": 2020,
      "season": null,
      "parameter": "pH",
      "actual_value": "7.1-7.9",
      "mean": null,
      "std_dev": null,
      "unit": null,
      "source": "Table 7",
      "notes": "Data from CPCB (2020) (CPCB 2021 annexure VI (a))."
    },
    {
      "location": "Nizamuddin",
      "date": null,
      "month": null,
      "year": 2020,
      "season": null,
      "parameter": "Dissolved Oxygen",
      "actual_value": "BDL-2.4",
      "mean": null,
      "std_dev": null,
      "unit": "mg/L",
      "source": "Table 7",
      "notes": "Data from CPCB (2020) (CPCB 2021 annexure VI (a)). BDL value for DO is 3.0 mg/L as per table footnote."
    },
    {
      "location": "Nizamuddin",
      "date": null,
      "month": null,
      "year": 2020,
      "season": null,
      "parameter": "Electrical Conductivity",
      "actual_value": "460-1641",
      "mean": null,
      "std_dev": null,
      "unit": "\u00b5mhos/cm",
      "source": "Table 7",
      "notes": "Data from CPCB (2020) (CPCB 2021 annexure VI (a))."
    },
    {
      "location": "Nizamuddin",
      "date": null,
      "month": null,
      "year": 2020,
      "season": null,
      "parameter": "Biochemical Oxygen Demand",
      "actual_value": "5.6-57.0",
      "mean": null,
      "std_dev": null,
      "unit": "mg/L",
      "source": "Table 7",
      "notes": "Data from CPCB (2020) (CPCB 2021 annexure VI (a))."
    },
    {
      "location": "Nizamuddin",
      "date": null,
      "month": null,
      "year": 2020,
      "season": null,
      "parameter": "Fecal Coliform",
      "actual_value": "210,000-11000000",
      "mean": null,
      "std_dev": null,
      "unit": "MPN/100 mL",
      "source": "Table 7",
      "notes": "Data from CPCB (2020) (CPCB 2021 annexure VI (a))."
    },
    {
      "location": "Nizamuddin",
      "date": null,
      "month": null,
      "year": 2020,
      "season": null,
      "parameter": "Total Coliform",
      "actual_value": "700,000-28000000",
      "mean": null,
      "std_dev": null,
      "unit": "MPN/100 mL",
      "source": "Table 7",
      "notes": "Data from CPCB (2020) (CPCB 2021 annexure VI (a))."
    },
    {
      "location": "Okhla Bridge (Inlet of Agra Canal)",
      "date": null,
      "month": null,
      "year": 2020,
      "season": null,
      "parameter": "Temperature",
      "actual_value": "15-31",
      "mean": null,
      "std_dev": null,
      "unit": "\u00b0C",
      "source": "Table 7",
      "notes": "Data from CPCB (2020) (CPCB 2021 annexure VI (a))."
    },
    {
      "location": "Okhla Bridge (Inlet of Agra Canal)",
      "date": null,
      "month": null,
      "year": 2020,
      "season": null,
      "parameter": "pH",
      "actual_value": "7.1-7.9",
      "mean": null,
      "std_dev": null,
      "unit": null,
      "source": "Table 7",
      "notes": "Data from CPCB (2020) (CPCB 2021 annexure VI (a))."
    },
    {
      "location": "Okhla Bridge (Inlet of Agra Canal)",
      "date": null,
      "month": null,
      "year": 2020,
      "season": null,
      "parameter": "Dissolved Oxygen",
      "actual_value": "BDL-2.6",
      "mean": null,
      "std_dev": null,
      "unit": "mg/L",
      "source": "Table 7",
      "notes": "Data from CPCB (2020) (CPCB 2021 annexure VI (a)). BDL value for DO is 3.0 mg/L as per table footnote."
    },
    {
      "location": "Okhla Bridge (Inlet of Agra Canal)",
      "date": null,
      "month": null,
      "year": 2020,
      "season": null,
      "parameter": "Electrical Conductivity",
      "actual_value": "488-1526",
      "mean": null,
      "std_dev": null,
      "unit": "\u00b5mhos/cm",
      "source": "Table 7",
      "notes": "Data from CPCB (2020) (CPCB 2021 annexure VI (a))."
    },
    {
      "location": "Okhla Bridge (Inlet of Agra Canal)",
      "date": null,
      "month": null,
      "year": 2020,
      "season": null,
      "parameter": "Biochemical Oxygen Demand",
      "actual_value": "5.6-27.0",
      "mean": null,
      "std_dev": null,
      "unit": "mg/L",
      "source": "Table 7",
      "notes": "Data from CPCB (2020) (CPCB 2021 annexure VI (a))."
    },
    {
      "location": "Okhla Bridge (Inlet of Agra Canal)",
      "date": null,
      "month": null,
      "year": 2020,
      "season": null,
      "parameter": "Fecal Coliform",
      "actual_value": "78,000-3300000",
      "mean": null,
      "std_dev": null,
      "unit": "MPN/100 mL",
      "source": "Table 7",
      "notes": "Data from CPCB (2020) (CPCB 2021 annexure VI (a))."
    },
    {
      "location": "Okhla Bridge (Inlet of Agra Canal)",
      "date": null,
      "month": null,
      "year": 2020,
      "season": null,
      "parameter": "Total Coliform",
      "actual_value": "350,000-16000000",
      "mean": null,
      "std_dev": null,
      "unit": "MPN/100 mL",
      "source": "Table 7",
      "notes": "Data from CPCB (2020) (CPCB 2021 annexure VI (a))."
    },
    {
      "location": "Okhla After Meeting of Shahdara Drain",
      "date": null,
      "month": null,
      "year": 2020,
      "season": null,
      "parameter": "Temperature",
      "actual_value": "15-33",
      "mean": null,
      "std_dev": null,
      "unit": "\u00b0C",
      "source": "Table 7",
      "notes": "Data from CPCB (2020) (CPCB 2021 annexure VI (a))."
    },
    {
      "location": "Okhla After Meeting of Shahdara Drain",
      "date": null,
      "month": null,
      "year": 2020,
      "season": null,
      "parameter": "pH",
      "actual_value": "7.2-7.8",
      "mean": null,
      "std_dev": null,
      "unit": null,
      "source": "Table 7",
      "notes": "Data from CPCB (2020) (CPCB 2021 annexure VI (a))."
    },
    {
      "location": "Okhla After Meeting of Shahdara Drain",
      "date": null,
      "month": null,
      "year": 2020,
      "season": null,
      "parameter": "Dissolved Oxygen",
      "actual_value": "BDL-5.6",
      "mean": null,
      "std_dev": null,
      "unit": "mg/L",
      "source": "Table 7",
      "notes": "Data from CPCB (2020) (CPCB 2021 annexure VI (a)). BDL value for DO is 3.0 mg/L as per table footnote."
    },
    {
      "location": "Okhla After Meeting of Shahdara Drain",
      "date": null,
      "month": null,
      "year": 2020,
      "season": null,
      "parameter": "Electrical Conductivity",
      "actual_value": "499-1773",
      "mean": null,
      "std_dev": null,
      "unit": "\u00b5mhos/cm",
      "source": "Table 7",
      "notes": "Data from CPCB (2020) (CPCB 2021 annexure VI (a))."
    },
    {
      "location": "Okhla After Meeting of Shahdara Drain",
      "date": null,
      "month": null,
      "year": 2020,
      "season": null,
      "parameter": "Biochemical Oxygen Demand",
      "actual_value": "7.7-114.0",
      "mean": null,
      "std_dev": null,
      "unit": "mg/L",
      "source": "Table 7",
      "notes": "Data from CPCB (2020) (CPCB 2021 annexure VI (a))."
    },
    {
      "location": "Okhla After Meeting of Shahdara Drain",
      "date": null,
      "month": null,
      "year": 2020,
      "season": null,
      "parameter": "Fecal Coliform",
      "actual_value": "68,000-7900000",
      "mean": null,
      "std_dev": null,
      "unit": "MPN/100 mL",
      "source": "Table 7",
      "notes": "Data from CPCB (2020) (CPCB 2021 annexure VI (a))."
    },
    {
      "location": "Okhla After Meeting of Shahdara Drain",
      "date": null,
      "month": null,
      "year": 2020,
      "season": null,
      "parameter": "Total Coliform",
      "actual_value": "490,000-35000000",
      "mean": null,
      "std_dev": null,
      "unit": "MPN/100 mL",
      "source": "Table 7",
      "notes": "Data from CPCB (2020) (CPCB 2021 annexure VI (a))."
    },
    {
      "location": "Agra Canal at Madanpur Khadar",
      "date": null,
      "month": null,
      "year": 2020,
      "season": null,
      "parameter": "Temperature",
      "actual_value": "15-31",
      "mean": null,
      "std_dev": null,
      "unit": "\u00b0C",
      "source": "Table 7",
      "notes": "Data from CPCB (2020) (CPCB 2021 annexure VI (a))."
    },
    {
      "location": "Agra Canal at Madanpur Khadar",
      "date": null,
      "month": null,
      "year": 2020,
      "season": null,
      "parameter": "pH",
      "actual_value": "7.1-7.8",
      "mean": null,
      "std_dev": null,
      "unit": null,
      "source": "Table 7",
      "notes": "Data from CPCB (2020) (CPCB 2021 annexure VI (a))."
    },
    {
      "location": "Agra Canal at Madanpur Khadar",
      "date": null,
      "month": null,
      "year": 2020,
      "season": null,
      "parameter": "Dissolved Oxygen",
      "actual_value": "BDL-1.4",
      "mean": null,
      "std_dev": null,
      "unit": "mg/L",
      "source": "Table 7",
      "notes": "Data from CPCB (2020) (CPCB 2021 annexure VI (a)). BDL value for DO is 3.0 mg/L as per table footnote."
    },
    {
      "location": "Agra Canal at Madanpur Khadar",
      "date": null,
      "month": null,
      "year": 2020,
      "season": null,
      "parameter": "Electrical Conductivity",
      "actual_value": "573-1541",
      "mean": null,
      "std_dev": null,
      "unit": "\u00b5mhos/cm",
      "source": "Table 7",
      "notes": "Data from CPCB (2020) (CPCB 2021 annexure VI (a))."
    },
    {
      "location": "Agra Canal at Madanpur Khadar",
      "date": null,
      "month": null,
      "year": 2020,
      "season": null,
      "parameter": "Biochemical Oxygen Demand",
      "actual_value": "11.4-32",
      "mean": null,
      "std_dev": null,
      "unit": "mg/L",
      "source": "Table 7",
      "notes": "Data from CPCB (2020) (CPCB 2021 annexure VI (a))."
    },
    {
      "location": "Agra Canal at Madanpur Khadar",
      "date": null,
      "month": null,
      "year": 2020,
      "season": null,
      "parameter": "Fecal Coliform",
      "actual_value": "330,000-4900000",
      "mean": null,
      "std_dev": null,
      "unit": "MPN/100 mL",
      "source": "Table 7",
      "notes": "Data from CPCB (2020) (CPCB 2021 annexure VI (a))."
    },
    {
      "location": "Agra Canal at Madanpur Khadar",
      "date": null,
      "month": null,
      "year": 2020,
      "season": null,
      "parameter": "Total Coliform",
      "actual_value": "1,100,000-24000000",
      "mean": null,
      "std_dev": null,
      "unit": "MPN/100 mL",
      "source": "Table 7",
      "notes": "Data from CPCB (2020) (CPCB 2021 annexure VI (a))."
    },
    {
      "location": "Mazawali",
      "date": null,
      "month": null,
      "year": 2020,
      "season": null,
      "parameter": "Temperature",
      "actual_value": "14",
      "mean": null,
      "std_dev": null,
      "unit": "\u00b0C",
      "source": "Table 7",
      "notes": "Data from CPCB (2020) (CPCB 2021 annexure VI (a))."
    },
    {
      "location": "Mazawali",
      "date": null,
      "month": null,
      "year": 2020,
      "season": null,
      "parameter": "pH",
      "actual_value": "6.4-8.1",
      "mean": null,
      "std_dev": null,
      "unit": null,
      "source": "Table 7",
      "notes": "Data from CPCB (2020) (CPCB 2021 annexure VI (a))."
    },
    {
      "location": "Mazawali",
      "date": null,
      "month": null,
      "year": 2020,
      "season": null,
      "parameter": "Dissolved Oxygen",
      "actual_value": "BDL-2.3",
      "mean": null,
      "std_dev": null,
      "unit": "mg/L",
      "source": "Table 7",
      "notes": "Data from CPCB (2020) (CPCB 2021 annexure VI (a)). BDL value for DO is 3.0 mg/L as per table footnote."
    },
    {
      "location": "Mazawali",
      "date": null,
      "month": null,
      "year": 2020,
      "season": null,
      "parameter": "Electrical Conductivity",
      "actual_value": "978-1719",
      "mean": null,
      "std_dev": null,
      "unit": "\u00b5mhos/cm",
      "source": "Table 7",
      "notes": "Data from CPCB (2020) (CPCB 2021 annexure VI (a))."
    },
    {
      "location": "Mazawali",
      "date": null,
      "month": null,
      "year": 2020,
      "season": null,
      "parameter": "Biochemical Oxygen Demand",
      "actual_value": "8.7-59.0",
      "mean": null,
      "std_dev": null,
      "unit": "mg/L",
      "source": "Table 7",
      "notes": "Data from CPCB (2020) (CPCB 2021 annexure VI (a))."
    },
    {
      "location": "Mazawali",
      "date": null,
      "month": null,
      "year": 2020,
      "season": null,
      "parameter": "Fecal Coliform",
      "actual_value": "680-4900000",
      "mean": null,
      "std_dev": null,
      "unit": "MPN/100 mL",
      "source": "Table 7",
      "notes": "Data from CPCB (2020) (CPCB 2021 annexure VI (a))."
    },
    {
      "location": "Mazawali",
      "date": null,
      "month": null,
      "year": 2020,
      "season": null,
      "parameter": "Total Coliform",
      "actual_value": "3300-9200000",
      "mean": null,
      "std_dev": null,
      "unit": "MPN/100 mL",
      "source": "Table 7",
      "notes": "Data from CPCB (2020) (CPCB 2021 annexure VI (a))."
    },
    {
      "location": "Shahpur",
      "date": null,
      "month": null,
      "year": 2020,
      "season": null,
      "parameter": "Temperature",
      "actual_value": "14-32",
      "mean": null,
      "std_dev": null,
      "unit": "\u00b0C",
      "source": "Table 7",
      "notes": "Data from CPCB (2020) (CPCB 2021 annexure VI (a))."
    },
    {
      "location": "Shahpur",
      "date": null,
      "month": null,
      "year": 2020,
      "season": null,
      "parameter": "pH",
      "actual_value": "7.1-7.5",
      "mean": null,
      "std_dev": null,
      "unit": null,
      "source": "Table 7",
      "notes": "Data from CPCB (2020) (CPCB 2021 annexure VI (a))."
    },
    {
      "location": "Shahpur",
      "date": null,
      "month": null,
      "year": 2020,
      "season": null,
      "parameter": "Dissolved Oxygen",
      "actual_value": "4.6-6.9",
      "mean": null,
      "std_dev": null,
      "unit": "mg/L",
      "source": "Table 7",
      "notes": "Data from CPCB (2020) (CPCB 2021 annexure VI (a)). BDL value for DO is 3.0 mg/L as per table footnote."
    },
    {
      "location": "Shahpur",
      "date": null,
      "month": null,
      "year": 2020,
      "season": null,
      "parameter": "Biochemical Oxygen Demand",
      "actual_value": "5.8-10.0",
      "mean": null,
      "std_dev": null,
      "unit": "mg/L",
      "source": "Table 7",
      "notes": "Data from CPCB (2020) (CPCB 2021 annexure VI (a))."
    },
    {
      "location": "Shahpur",
      "date": null,
      "month": null,
      "year": 2020,
      "season": null,
      "parameter": "Fecal Coliform",
      "actual_value": "31,000-85000",
      "mean": null,
      "std_dev": null,
      "unit": "MPN/100 mL",
      "source": "Table 7",
      "notes": "Data from CPCB (2020) (CPCB 2021 annexure VI (a))."
    },
    {
      "location": "Shahpur",
      "date": null,
      "month": null,
      "year": 2020,
      "season": null,
      "parameter": "Total Coliform",
      "actual_value": "53,000-110000",
      "mean": null,
      "std_dev": null,
      "unit": "MPN/100 mL",
      "source": "Table 7",
      "notes": "Data from CPCB (2020) (CPCB 2021 annexure VI (a))."
    },
    {
      "location": "Kesighat, Vrindavan",
      "date": null,
      "month": null,
      "year": 2020,
      "season": null,
      "parameter": "Temperature",
      "actual_value": "15-32",
      "mean": null,
      "std_dev": null,
      "unit": "\u00b0C",
      "source": "Table 7",
      "notes": "Data from CPCB (2020) (CPCB 2021 annexure VI (a))."
    },
    {
      "location": "Kesighat, Vrindavan",
      "date": null,
      "month": null,
      "year": 2020,
      "season": null,
      "parameter": "pH",
      "actual_value": "7.1-7.6",
      "mean": null,
      "std_dev": null,
      "unit": null,
      "source": "Table 7",
      "notes": "Data from CPCB (2020) (CPCB 2021 annexure VI (a))."
    },
    {
      "location": "Kesighat, Vrindavan",
      "date": null,
      "month": null,
      "year": 2020,
      "season": null,
      "parameter": "Dissolved Oxygen",
      "actual_value": "4.0-7.6",
      "mean": null,
      "std_dev": null,
      "unit": "mg/L",
      "source": "Table 7",
      "notes": "Data from CPCB (2020) (CPCB 2021 annexure VI (a)). BDL value for DO is 3.0 mg/L as per table footnote."
    },
    {
      "location": "Kesighat, Vrindavan",
      "date": null,
      "month": null,
      "year": 2020,
      "season": null,
      "parameter": "Biochemical Oxygen Demand",
      "actual_value": "6.0-10.4",
      "mean": null,
      "std_dev": null,
      "unit": "mg/L",
      "source": "Table 7",
      "notes": "Data from CPCB (2020) (CPCB 2021 annexure VI (a))."
    },
    {
      "location": "Kesighat, Vrindavan",
      "date": null,
      "month": null,
      "year": 2020,
      "season": null,
      "parameter": "Fecal Coliform",
      "actual_value": "24,000-65000",
      "mean": null,
      "std_dev": null,
      "unit": "MPN/100 mL",
      "source": "Table 7",
      "notes": "Data from CPCB (2020) (CPCB 2021 annexure VI (a))."
    },
    {
      "location": "Kesighat, Vrindavan",
      "date": null,
      "month": null,
      "year": 2020,
      "season": null,
      "parameter": "Total Coliform",
      "actual_value": "46,000-88000",
      "mean": null,
      "std_dev": null,
      "unit": "MPN/100 mL",
      "source": "Table 7",
      "notes": "Data from CPCB (2020) (CPCB 2021 annexure VI (a))."
    },
    {
      "location": "Mathura U/S",
      "date": null,
      "month": null,
      "year": 2020,
      "season": null,
      "parameter": "Temperature",
      "actual_value": "13",
      "mean": null,
      "std_dev": null,
      "unit": "\u00b0C",
      "source": "Table 7",
      "notes": "Data from CPCB (2020) (CPCB 2021 annexure VI (a))."
    },
    {
      "location": "Mathura U/S",
      "date": null,
      "month": null,
      "year": 2020,
      "season": null,
      "parameter": "pH",
      "actual_value": "6.5-8.5",
      "mean": null,
      "std_dev": null,
      "unit": null,
      "source": "Table 7",
      "notes": "Data from CPCB (2020) (CPCB 2021 annexure VI (a))."
    },
    {
      "location": "Mathura U/S",
      "date": null,
      "month": null,
      "year": 2020,
      "season": null,
      "parameter": "Dissolved Oxygen",
      "actual_value": "BDL-4.6",
      "mean": null,
      "std_dev": null,
      "unit": "mg/L",
      "source": "Table 7",
      "notes": "Data from CPCB (2020) (CPCB 2021 annexure VI (a)). BDL value for DO is 3.0 mg/L as per table footnote."
    },
    {
      "location": "Mathura U/S",
      "date": null,
      "month": null,
      "year": 2020,
      "season": null,
      "parameter": "Electrical Conductivity",
      "actual_value": "1096-1816",
      "mean": null,
      "std_dev": null,
      "unit": "\u00b5mhos/cm",
      "source": "Table 7",
      "notes": "Data from CPCB (2020) (CPCB 2021 annexure VI (a))."
    },
    {
      "location": "Mathura U/S",
      "date": null,
      "month": null,
      "year": 2020,
      "season": null,
      "parameter": "Biochemical Oxygen Demand",
      "actual_value": "7.3-30.0",
      "mean": null,
      "std_dev": null,
      "unit": "mg/L",
      "source": "Table 7",
      "notes": "Data from CPCB (2020) (CPCB 2021 annexure VI (a))."
    },
    {
      "location": "Mathura U/S",
      "date": null,
      "month": null,
      "year": 2020,
      "season": null,
      "parameter": "Fecal Coliform",
      "actual_value": "400-920000",
      "mean": null,
      "std_dev": null,
      "unit": "MPN/100 mL",
      "source": "Table 7",
      "notes": "Data from CPCB (2020) (CPCB 2021 annexure VI (a))."
    },
    {
      "location": "Mathura U/S",
      "date": null,
      "month": null,
      "year": 2020,
      "season": null,
      "parameter": "Total Coliform",
      "actual_value": "1100-9200000",
      "mean": null,
      "std_dev": null,
      "unit": "MPN/100 mL",
      "source": "Table 7",
      "notes": "Data from CPCB (2020) (CPCB 2021 annexure VI (a))."
    },
    {
      "location": "Vishramghat, Mathura",
      "date": null,
      "month": null,
      "year": 2020,
      "season": null,
      "parameter": "Temperature",
      "actual_value": "14-32",
      "mean": null,
      "std_dev": null,
      "unit": "\u00b0C",
      "source": "Table 7",
      "notes": "Data from CPCB (2020) (CPCB 2021 annexure VI (a))."
    },
    {
      "location": "Vishramghat, Mathura",
      "date": null,
      "month": null,
      "year": 2020,
      "season": null,
      "parameter": "pH",
      "actual_value": "6.9-7.6",
      "mean": null,
      "std_dev": null,
      "unit": null,
      "source": "Table 7",
      "notes": "Data from CPCB (2020) (CPCB 2021 annexure VI (a))."
    },
    {
      "location": "Vishramghat, Mathura",
      "date": null,
      "month": null,
      "year": 2020,
      "season": null,
      "parameter": "Dissolved Oxygen",
      "actual_value": "4.1-7.4",
      "mean": null,
      "std_dev": null,
      "unit": "mg/L",
      "source": "Table 7",
      "notes": "Data from CPCB (2020) (CPCB 2021 annexure VI (a)). BDL value for DO is 3.0 mg/L as per table footnote."
    },
    {
      "location": "Vishramghat, Mathura",
      "date": null,
      "month": null,
      "year": 2020,
      "season": null,
      "parameter": "Biochemical Oxygen Demand",
      "actual_value": "6.8-12.0",
      "mean": null,
      "std_dev": null,
      "unit": "mg/L",
      "source": "Table 7",
      "notes": "Data from CPCB (2020) (CPCB 2021 annexure VI (a))."
    },
    {
      "location": "Vishramghat, Mathura",
      "date": null,
      "month": null,
      "year": 2020,
      "season": null,
      "parameter": "Fecal Coliform",
      "actual_value": "31,000-92000",
      "mean": null,
      "std_dev": null,
      "unit": "MPN/100 mL",
      "source": "Table 7",
      "notes": "Data from CPCB (2020) (CPCB 2021 annexure VI (a))."
    },
    {
      "location": "Vishramghat, Mathura",
      "date": null,
      "month": null,
      "year": 2020,
      "season": null,
      "parameter": "Total Coliform",
      "actual_value": "54,000-140000",
      "mean": null,
      "std_dev": null,
      "unit": "MPN/100 mL",
      "source": "Table 7",
      "notes": "Data from CPCB (2020) (CPCB 2021 annexure VI (a))."
    },
    {
      "location": "Mathura D/S",
      "date": null,
      "month": null,
      "year": 2020,
      "season": null,
      "parameter": "Temperature",
      "actual_value": "12",
      "mean": null,
      "std_dev": null,
      "unit": "\u00b0C",
      "source": "Table 7",
      "notes": "Data from CPCB (2020) (CPCB 2021 annexure VI (a))."
    },
    {
      "location": "Mathura D/S",
      "date": null,
      "month": null,
      "year": 2020,
      "season": null,
      "parameter": "pH",
      "actual_value": "6.5-8.3",
      "mean": null,
      "std_dev": null,
      "unit": null,
      "source": "Table 7",
      "notes": "Data from CPCB (2020) (CPCB 2021 annexure VI (a))."
    },
    {
      "location": "Mathura D/S",
      "date": null,
      "month": null,
      "year": 2020,
      "season": null,
      "parameter": "Dissolved Oxygen",
      "actual_value": "1.6-6.8",
      "mean": null,
      "std_dev": null,
      "unit": "mg/L",
      "source": "Table 7",
      "notes": "Data from CPCB (2020) (CPCB 2021 annexure VI (a)). BDL value for DO is 3.0 mg/L as per table footnote."
    },
    {
      "location": "Mathura D/S",
      "date": null,
      "month": null,
      "year": 2020,
      "season": null,
      "parameter": "Electrical Conductivity",
      "actual_value": "1195-1903",
      "mean": null,
      "std_dev": null,
      "unit": "\u00b5mhos/cm",
      "source": "Table 7",
      "notes": "Data from CPCB (2020) (CPCB 2021 annexure VI (a))."
    },
    {
      "location": "Mathura D/S",
      "date": null,
      "month": null,
      "year": 2020,
      "season": null,
      "parameter": "Biochemical Oxygen Demand",
      "actual_value": "6.9-21.0",
      "mean": null,
      "std_dev": null,
      "unit": "mg/L",
      "source": "Table 7",
      "notes": "Data from CPCB (2020) (CPCB 2021 annexure VI (a))."
    },
    {
      "location": "Mathura D/S",
      "date": null,
      "month": null,
      "year": 2020,
      "season": null,
      "parameter": "Fecal Coliform",
      "actual_value": "1700-170000",
      "mean": null,
      "std_dev": null,
      "unit": "MPN/100 mL",
      "source": "Table 7",
      "notes": "Data from CPCB (2020) (CPCB 2021 annexure VI (a))."
    },
    {
      "location": "Mathura D/S",
      "date": null,
      "month": null,
      "year": 2020,
      "season": null,
      "parameter": "Total Coliform",
      "actual_value": "2200-1400000",
      "mean": null,
      "std_dev": null,
      "unit": "MPN/100 mL",
      "source": "Table 7",
      "notes": "Data from CPCB (2020) (CPCB 2021 annexure VI (a))."
    },
    {
      "location": "Agra U/S",
      "date": null,
      "month": null,
      "year": 2020,
      "season": null,
      "parameter": "Temperature",
      "actual_value": "12",
      "mean": null,
      "std_dev": null,
      "unit": "\u00b0C",
      "source": "Table 7",
      "notes": "Data from CPCB (2020) (CPCB 2021 annexure VI (a))."
    },
    {
      "location": "Agra U/S",
      "date": null,
      "month": null,
      "year": 2020,
      "season": null,
      "parameter": "pH",
      "actual_value": "6.5-8.5",
      "mean": null,
      "std_dev": null,
      "unit": null,
      "source": "Table 7",
      "notes": "Data from CPCB (2020) (CPCB 2021 annexure VI (a))."
    },
    {
      "location": "Agra U/S",
      "date": null,
      "month": null,
      "year": 2020,
      "season": null,
      "parameter": "Dissolved Oxygen",
      "actual_value": "1.4-9.6",
      "mean": null,
      "std_dev": null,
      "unit": "mg/L",
      "source": "Table 7",
      "notes": "Data from CPCB (2020) (CPCB 2021 annexure VI (a)). BDL value for DO is 3.0 mg/L as per table footnote."
    },
    {
      "location": "Agra U/S",
      "date": null,
      "month": null,
      "year": 2020,
      "season": null,
      "parameter": "Electrical Conductivity",
      "actual_value": "1154-1872",
      "mean": null,
      "std_dev": null,
      "unit": "\u00b5mhos/cm",
      "source": "Table 7",
      "notes": "Data from CPCB (2020) (CPCB 2021 annexure VI (a))."
    },
    {
      "location": "Agra U/S",
      "date": null,
      "month": null,
      "year": 2020,
      "season": null,
      "parameter": "Biochemical Oxygen Demand",
      "actual_value": "4.7-25.0",
      "mean": null,
      "std_dev": null,
      "unit": "mg/L",
      "source": "Table 7",
      "notes": "Data from CPCB (2020) (CPCB 2021 annexure VI (a))."
    },
    {
      "location": "Agra U/S",
      "date": null,
      "month": null,
      "year": 2020,
      "season": null,
      "parameter": "Fecal Coliform",
      "actual_value": "220-3300000",
      "mean": null,
      "std_dev": null,
      "unit": "MPN/100 mL",
      "source": "Table 7",
      "notes": "Data from CPCB (2020) (CPCB 2021 annexure VI (a))."
    },
    {
      "location": "Agra U/S",
      "date": null,
      "month": null,
      "year": 2020,
      "season": null,
      "parameter": "Total Coliform",
      "actual_value": "2200-7900000",
      "mean": null,
      "std_dev": null,
      "unit": "MPN/100 mL",
      "source": "Table 7",
      "notes": "Data from CPCB (2020) (CPCB 2021 annexure VI (a))."
    },
    {
      "location": "D/S of Agra",
      "date": null,
      "month": null,
      "year": 2020,
      "season": null,
      "parameter": "pH",
      "actual_value": "6.5-8.7",
      "mean": null,
      "std_dev": null,
      "unit": null,
      "source": "Table 7",
      "notes": "Data from CPCB (2020) (CPCB 2021 annexure VI (a))."
    },
    {
      "location": "D/S of Agra",
      "date": null,
      "month": null,
      "year": 2020,
      "season": null,
      "parameter": "Dissolved Oxygen",
      "actual_value": "3.8-16.2",
      "mean": null,
      "std_dev": null,
      "unit": "mg/L",
      "source": "Table 7",
      "notes": "Data from CPCB (2020) (CPCB 2021 annexure VI (a)). BDL value for DO is 3.0 mg/L as per table footnote."
    },
    {
      "location": "D/S of Agra",
      "date": null,
      "month": null,
      "year": 2020,
      "season": null,
      "parameter": "Electrical Conductivity",
      "actual_value": "875-1920",
      "mean": null,
      "std_dev": null,
      "unit": "\u00b5mhos/cm",
      "source": "Table 7",
      "notes": "Data from CPCB (2020) (CPCB 2021 annexure VI (a))."
    },
    {
      "location": "D/S of Agra",
      "date": null,
      "month": null,
      "year": 2020,
      "season": null,
      "parameter": "Biochemical Oxygen Demand",
      "actual_value": "9.1-25.0",
      "mean": null,
      "std_dev": null,
      "unit": "mg/L",
      "source": "Table 7",
      "notes": "Data from CPCB (2020) (CPCB 2021 annexure VI (a))."
    },
    {
      "location": "D/S of Agra",
      "date": null,
      "month": null,
      "year": 2020,
      "season": null,
      "parameter": "Fecal Coliform",
      "actual_value": "450-6100000",
      "mean": null,
      "std_dev": null,
      "unit": "MPN/100 mL",
      "source": "Table 7",
      "notes": "Data from CPCB (2020) (CPCB 2021 annexure VI (a))."
    },
    {
      "location": "D/S of Agra",
      "date": null,
      "month": null,
      "year": 2020,
      "season": null,
      "parameter": "Total Coliform",
      "actual_value": "2200-32000000",
      "mean": null,
      "std_dev": null,
      "unit": "MPN/100 mL",
      "source": "Table 7",
      "notes": "Data from CPCB (2020) (CPCB 2021 annexure VI (a))."
    },
    {
      "location": "Bateswar",
      "date": null,
      "month": null,
      "year": 2020,
      "season": null,
      "parameter": "pH",
      "actual_value": "7.8-7.9",
      "mean": null,
      "std_dev": null,
      "unit": null,
      "source": "Table 7",
      "notes": "Data from CPCB (2020) (CPCB 2021 annexure VI (a))."
    },
    {
      "location": "Bateswar",
      "date": null,
      "month": null,
      "year": 2020,
      "season": null,
      "parameter": "Dissolved Oxygen",
      "actual_value": "2.6-9.2",
      "mean": null,
      "std_dev": null,
      "unit": "mg/L",
      "source": "Table 7",
      "notes": "Data from CPCB (2020) (CPCB 2021 annexure VI (a)). BDL value for DO is 3.0 mg/L as per table footnote."
    },
    {
      "location": "Bateswar",
      "date": null,
      "month": null,
      "year": 2020,
      "season": null,
      "parameter": "Electrical Conductivity",
      "actual_value": "1054-1471",
      "mean": null,
      "std_dev": null,
      "unit": "\u00b5mhos/cm",
      "source": "Table 7",
      "notes": "Data from CPCB (2020) (CPCB 2021 annexure VI (a))."
    },
    {
      "location": "Bateswar",
      "date": null,
      "month": null,
      "year": 2020,
      "season": null,
      "parameter": "Biochemical Oxygen Demand",
      "actual_value": "14.0-20.0",
      "mean": null,
      "std_dev": null,
      "unit": "mg/L",
      "source": "Table 7",
      "notes": "Data from CPCB (2020) (CPCB 2021 annexure VI (a))."
    },
    {
      "location": "Bateswar",
      "date": null,
      "month": null,
      "year": 2020,
      "season": null,
      "parameter": "Fecal Coliform",
      "actual_value": "450-1400",
      "mean": null,
      "std_dev": null,
      "unit": "MPN/100 mL",
      "source": "Table 7",
      "notes": "Data from CPCB (2020) (CPCB 2021 annexure VI (a))."
    },
    {
      "location": "Bateswar",
      "date": null,
      "month": null,
      "year": 2020,
      "season": null,
      "parameter": "Total Coliform",
      "actual_value": "3300-13000",
      "mean": null,
      "std_dev": null,
      "unit": "MPN/100 mL",
      "source": "Table 7",
      "notes": "Data from CPCB (2020) (CPCB 2021 annexure VI (a))."
    },
    {
      "location": "Etawah",
      "date": null,
      "month": null,
      "year": 2020,
      "season": null,
      "parameter": "pH",
      "actual_value": "7.7-7.9",
      "mean": null,
      "std_dev": null,
      "unit": null,
      "source": "Table 7",
      "notes": "Data from CPCB (2020) (CPCB 2021 annexure VI (a))."
    },
    {
      "location": "Etawah",
      "date": null,
      "month": null,
      "year": 2020,
      "season": null,
      "parameter": "Dissolved Oxygen",
      "actual_value": "7.3-7.3",
      "mean": null,
      "std_dev": null,
      "unit": "mg/L",
      "source": "Table 7",
      "notes": "Data from CPCB (2020) (CPCB 2021 annexure VI (a)). BDL value for DO is 3.0 mg/L as per table footnote."
    },
    {
      "location": "Etawah",
      "date": null,
      "month": null,
      "year": 2020,
      "season": null,
      "parameter": "Electrical Conductivity",
      "actual_value": "1288-1507",
      "mean": null,
      "std_dev": null,
      "unit": "\u00b5mhos/cm",
      "source": "Table 7",
      "notes": "Data from CPCB (2020) (CPCB 2021 annexure VI (a))."
    },
    {
      "location": "Etawah",
      "date": null,
      "month": null,
      "year": 2020,
      "season": null,
      "parameter": "Biochemical Oxygen Demand",
      "actual_value": "13.0-15.0",
      "mean": null,
      "std_dev": null,
      "unit": "mg/L",
      "source": "Table 7",
      "notes": "Data from CPCB (2020) (CPCB 2021 annexure VI (a))."
    },
    {
      "location": "Etawah",
      "date": null,
      "month": null,
      "year": 2020,
      "season": null,
      "parameter": "Fecal Coliform",
      "actual_value": "20-200",
      "mean": null,
      "std_dev": null,
      "unit": "MPN/100 mL",
      "source": "Table 7",
      "notes": "Data from CPCB (2020) (CPCB 2021 annexure VI (a))."
    },
    {
      "location": "Etawah",
      "date": null,
      "month": null,
      "year": 2020,
      "season": null,
      "parameter": "Total Coliform",
      "actual_value": "1300-1700",
      "mean": null,
      "std_dev": null,
      "unit": "MPN/100 mL",
      "source": "Table 7",
      "notes": "Data from CPCB (2020) (CPCB 2021 annexure VI (a))."
    },
    {
      "location": "Juhika B/C with Chambal, Etawah",
      "date": null,
      "month": null,
      "year": 2020,
      "season": null,
      "parameter": "pH",
      "actual_value": "7.7-8.2",
      "mean": null,
      "std_dev": null,
      "unit": null,
      "source": "Table 7",
      "notes": "Data from CPCB (2020) (CPCB 2021 annexure VI (a))."
    },
    {
      "location": "Juhika B/C with Chambal, Etawah",
      "date": null,
      "month": null,
      "year": 2020,
      "season": null,
      "parameter": "Dissolved Oxygen",
      "actual_value": "8.1-11.3",
      "mean": null,
      "std_dev": null,
      "unit": "mg/L",
      "source": "Table 7",
      "notes": "Data from CPCB (2020) (CPCB 2021 annexure VI (a)). BDL value for DO is 3.0 mg/L as per table footnote."
    },
    {
      "location": "Juhika B/C with Chambal, Etawah",
      "date": null,
      "month": null,
      "year": 2020,
      "season": null,
      "parameter": "Electrical Conductivity",
      "actual_value": "846-937",
      "mean": null,
      "std_dev": null,
      "unit": "\u00b5mhos/cm",
      "source": "Table 7",
      "notes": "Data from CPCB (2020) (CPCB 2021 annexure VI (a))."
    },
    {
      "location": "Juhika B/C with Chambal, Etawah",
      "date": null,
      "month": null,
      "year": 2020,
      "season": null,
      "parameter": "Biochemical Oxygen Demand",
      "actual_value": "8.7-13.0",
      "mean": null,
      "std_dev": null,
      "unit": "mg/L",
      "source": "Table 7",
      "notes": "Data from CPCB (2020) (CPCB 2021 annexure VI (a))."
    },
    {
      "location": "Juhika B/C with Chambal, Etawah",
      "date": null,
      "month": null,
      "year": 2020,
      "season": null,
      "parameter": "Fecal Coliform",
      "actual_value": "68-7800",
      "mean": null,
      "std_dev": null,
      "unit": "MPN/100 mL",
      "source": "Table 7",
      "notes": "Data from CPCB (2020) (CPCB 2021 annexure VI (a))."
    },
    {
      "location": "Juhika B/C with Chambal, Etawah",
      "date": null,
      "month": null,
      "year": 2020,
      "season": null,
      "parameter": "Total Coliform",
      "actual_value": "1700-220000",
      "mean": null,
      "std_dev": null,
      "unit": "MPN/100 mL",
      "source": "Table 7",
      "notes": "Data from CPCB (2020) (CPCB 2021 annexure VI (a))."
    },
    {
      "location": "Hamirpur",
      "date": null,
      "month": null,
      "year": 2020,
      "season": null,
      "parameter": "pH",
      "actual_value": "8.0-8.4",
      "mean": null,
      "std_dev": null,
      "unit": null,
      "source": "Table 7",
      "notes": "Data from CPCB (2020) (CPCB 2021 annexure VI (a))."
    },
    {
      "location": "Hamirpur",
      "date": null,
      "month": null,
      "year": 2020,
      "season": null,
      "parameter": "Dissolved Oxygen",
      "actual_value": "0.4-8.4",
      "mean": null,
      "std_dev": null,
      "unit": "mg/L",
      "source": "Table 7",
      "notes": "Data from CPCB (2020) (CPCB 2021 annexure VI (a)). BDL value for DO is 3.0 mg/L as per table footnote."
    },
    {
      "location": "Hamirpur",
      "date": null,
      "month": null,
      "year": 2020,
      "season": null,
      "parameter": "Electrical Conductivity",
      "actual_value": "750-832",
      "mean": null,
      "std_dev": null,
      "unit": "\u00b5mhos/cm",
      "source": "Table 7",
      "notes": "Data from CPCB (2020) (CPCB 2021 annexure VI (a))."
    },
    {
      "location": "Hamirpur",
      "date": null,
      "month": null,
      "year": 2020,
      "season": null,
      "parameter": "Biochemical Oxygen Demand",
      "actual_value": "2.8-6.0",
      "mean": null,
      "std_dev": null,
      "unit": "mg/L",
      "source": "Table 7",
      "notes": "Data from CPCB (2020) (CPCB 2021 annexure VI (a))."
    },
    {
      "location": "Hamirpur",
      "date": null,
      "month": null,
      "year": 2020,
      "season": null,
      "parameter": "Fecal Coliform",
      "actual_value": "330-2200",
      "mean": null,
      "std_dev": null,
      "unit": "MPN/100 mL",
      "source": "Table 7",
      "notes": "Data from CPCB (2020) (CPCB 2021 annexure VI (a))."
    },
    {
      "location": "Hamirpur",
      "date": null,
      "month": null,
      "year": 2020,
      "season": null,
      "parameter": "Total Coliform",
      "actual_value": "1300-13000",
      "mean": null,
      "std_dev": null,
      "unit": "MPN/100 mL",
      "source": "Table 7",
      "notes": "Data from CPCB (2020) (CPCB 2021 annexure VI (a))."
    },
    {
      "location": "Allahabad D/S (Balua Ghat)",
      "date": null,
      "month": null,
      "year": 2020,
      "season": null,
      "parameter": "Temperature",
      "actual_value": "22-27",
      "mean": null,
      "std_dev": null,
      "unit": "\u00b0C",
      "source": "Table 7",
      "notes": "Data from CPCB (2020) (CPCB 2021 annexure VI (a))."
    },
    {
      "location": "Allahabad D/S (Balua Ghat)",
      "date": null,
      "month": null,
      "year": 2020,
      "season": null,
      "parameter": "pH",
      "actual_value": "7.8-8.4",
      "mean": null,
      "std_dev": null,
      "unit": null,
      "source": "Table 7",
      "notes": "Data from CPCB (2020) (CPCB 2021 annexure VI (a))."
    },
    {
      "location": "Allahabad D/S (Balua Ghat)",
      "date": null,
      "month": null,
      "year": 2020,
      "season": null,
      "parameter": "Dissolved Oxygen",
      "actual_value": "7.3-11.5",
      "mean": null,
      "std_dev": null,
      "unit": "mg/L",
      "source": "Table 7",
      "notes": "Data from CPCB (2020) (CPCB 2021 annexure VI (a)). BDL value for DO is 3.0 mg/L as per table footnote."
    },
    {
      "location": "Allahabad D/S (Balua Ghat)",
      "date": null,
      "month": null,
      "year": 2020,
      "season": null,
      "parameter": "Electrical Conductivity",
      "actual_value": "418-725",
      "mean": null,
      "std_dev": null,
      "unit": "\u00b5mhos/cm",
      "source": "Table 7",
      "notes": "Data from CPCB (2020) (CPCB 2021 annexure VI (a))."
    },
    {
      "location": "Allahabad D/S (Balua Ghat)",
      "date": null,
      "month": null,
      "year": 2020,
      "season": null,
      "parameter": "Biochemical Oxygen Demand",
      "actual_value": "1.8-2.4",
      "mean": null,
      "std_dev": null,
      "unit": "mg/L",
      "source": "Table 7",
      "notes": "Data from CPCB (2020) (CPCB 2021 annexure VI (a))."
    },
    {
      "location": "Allahabad D/S (Balua Ghat)",
      "date": null,
      "month": null,
      "year": 2020,
      "season": null,
      "parameter": "Fecal Coliform",
      "actual_value": "310-2100",
      "mean": null,
      "std_dev": null,
      "unit": "MPN/100 mL",
      "source": "Table 7",
      "notes": "Data from CPCB (2020) (CPCB 2021 annexure VI (a))."
    },
    {
      "location": "Allahabad D/S (Balua Ghat)",
      "date": null,
      "month": null,
      "year": 2020,
      "season": null,
      "parameter": "Total Coliform",
      "actual_value": "1700-3900",
      "mean": null,
      "std_dev": null,
      "unit": "MPN/100 mL",
      "source": "Table 7",
      "notes": "Data from CPCB (2020) (CPCB 2021 annexure VI (a))."
    }
  ],
  "extraction_issues": []
}